webhook_logger/__init__.py
webhook_logger/slack.py
webhook_logger-0.2.0.dist-info/DESCRIPTION.rst
webhook_logger-0.2.0.dist-info/METADATA
webhook_logger-0.2.0.dist-info/RECORD
webhook_logger-0.2.0.dist-info/WHEEL
webhook_logger-0.2.0.dist-info/metadata.json
webhook_logger-0.2.0.dist-info/top_level.txt
