Metadata-Version: 2.0
Name: webhook-logger
Version: 0.2.0
Summary: A Python logger to send information to Webhooks
Home-page: https://github.com/founders4schools/python-webhook-logger
Author: Founders4Schools
Author-email: dev@founders4schools.org.uk
License: MIT license
Keywords: webhook_logger
Platform: UNKNOWN
Classifier: Development Status :: 2 - Pre-Alpha
Classifier: Intended Audience :: Developers
Classifier: License :: OSI Approved :: MIT License
Classifier: Natural Language :: English
Classifier: Programming Language :: Python :: 2
Classifier: Programming Language :: Python :: 2.6
Classifier: Programming Language :: Python :: 2.7
Classifier: Programming Language :: Python :: 3
Classifier: Programming Language :: Python :: 3.3
Classifier: Programming Language :: Python :: 3.4
Classifier: Programming Language :: Python :: 3.5
Requires-Dist: requests
